{
	"chapter": false,
	"closeTerminalSession": true,
	"contentType": "html",
	"files": [
		{
			"action": "open",
			"panel": 0,
			"path": "about-us.html"
		},
		{
			"action": "open",
			"panel": 0,
			"path": "contact-us.html"
		},
		{
			"action": "open",
			"panel": 0,
			"path": "table.html"
		},
		{
			"action": "open",
			"panel": 0,
			"path": "index.html"
		},
		{
			"action": "open",
			"panel": 1,
			"path": "#preview: about-us.html"
		},
		{
			"action": "open",
			"panel": 1,
			"path": "#preview: contact-us.html"
		},
		{
			"action": "open",
			"panel": 1,
			"path": "#preview: table.html"
		},
		{
			"action": "open",
			"panel": 1,
			"path": "#preview: index.html"
		}
	],
	"id": "a59584bc-2eff-e878-12e1-54b22824f734",
	"learningObjectives": "",
	"path": [
		"images",
		"index.html",
		"style.css",
		"table.html",
		"about-us.html",
		"contact-us.html"
	],
	"reset": [],
	"teacherOnly": false,
	"title": "Copy your nav menu into the other pages",
	"type": "page"
}